Metadata-Version: 2.1
Name: matrixpro
Version: 0.36
Summary: This is a python module for handling matrices, including matrix calculation, analysis and algorithms.
Home-page: https://github.com/Rainbow-Dreamer/matrixpro
Author: Rainbow-Dreamer
Author-email: 1036889495@qq.com
License: LGPLv2.1
Download-URL: https://github.com/Rainbow-Dreamer/matrixpro/archive/0.36.tar.gz
Keywords: matrix,mathematics,statistics
Platform: UNKNOWN
Classifier: Development Status :: 3 - Alpha
Classifier: Intended Audience :: Developers
Classifier: Topic :: Software Development :: Build Tools
Classifier: License :: OSI Approved :: GNU Lesser General Public License v2 or later (LGPLv2+)
Classifier: Programming Language :: Python :: 3.6
Classifier: Programming Language :: Python :: 3.7
Classifier: Programming Language :: Python :: 3.8
Classifier: Programming Language :: Python :: 3.9
Classifier: Programming Language :: Python :: 3.10
